email_sender_zone24x7/EmailSender.py
email_sender_zone24x7/__init__.py
email_sender_zone24x7-0.1.dist-info/LICENCE
email_sender_zone24x7-0.1.dist-info/METADATA
email_sender_zone24x7-0.1.dist-info/WHEEL
email_sender_zone24x7-0.1.dist-info/top_level.txt
email_sender_zone24x7-0.1.dist-info/RECORD
